asset_extraction_framework/Application.py
asset_extraction_framework/Asserts.py
asset_extraction_framework/CommandLine.py
asset_extraction_framework/Exceptions.py
asset_extraction_framework/File.py
asset_extraction_framework/__init__.py
asset_extraction_framework/Asset/Animation.py
asset_extraction_framework/Asset/Asset.py
asset_extraction_framework/Asset/BoundingBox.py
asset_extraction_framework/Asset/Image.py
asset_extraction_framework/Asset/Palette.py
asset_extraction_framework/Asset/Sound.py
asset_extraction_framework/Asset/__init__.py
asset_extraction_framework-0.9.7.dist-info/COPYING
asset_extraction_framework-0.9.7.dist-info/METADATA
asset_extraction_framework-0.9.7.dist-info/WHEEL
asset_extraction_framework-0.9.7.dist-info/top_level.txt
asset_extraction_framework-0.9.7.dist-info/RECORD
