Metadata-Version: 2.1
Name: asset_extraction_framework
Version: 0.9.7
Summary: Toolkit to help extract multimedia assets from legacy software
Author: npjg
License: GNU GENERAL PUBLIC LICENSE
Project-URL: Homepage, https://github.com/npjg/asset_extraction_framework
Project-URL: Repository, https://github.com/npjg/asset_extraction_framework
Keywords: struct,reverse-engineering,self-document
Classifier: License :: OSI Approved :: GNU General Public License v3 (GPLv3)
Classifier: Programming Language :: Python
Classifier: Programming Language :: Python :: 3
Requires-Python: >=3.9
License-File: COPYING
Requires-Dist: Pillow >=9.2.0
Requires-Dist: numpy >=1.23.0
Requires-Dist: jsons >=1.6.2
Requires-Dist: hexdump2 >=1.1
